myaiotgm/__init__.py
myaiotgm/client.py
myaiotgm/json_manager.py
myaiotgm-0.0.0.dist-info/LICENSE
myaiotgm-0.0.0.dist-info/METADATA
myaiotgm-0.0.0.dist-info/WHEEL
myaiotgm-0.0.0.dist-info/top_level.txt
myaiotgm-0.0.0.dist-info/RECORD
