Metadata-Version: 2.1
Name: myaiotgm
Version: 0.0.0
Author: unixtux
License: GNU GENERAL PUBLIC LICENSE
Requires-Python: >=3.8
License-File: LICENSE
Requires-Dist: aiotgm >=0.1.3
